{
    "url": "https://2e.aonprd.com/Feats.aspx?ID=1591",
    "name": "Patron's Truth",
    "source": "Advanced Player's Guide",
    "rarity": "Common",
    "traits": [
        "Witch"
    ],
    "level": 20,
    "prereq": "Patron's Gift",
    "summary": "You have mastered the greatest secrets of your patron's magic and learned a fundamental truth about your patron, even if their identity still remains a mystery.",
    "description": "You have mastered the greatest secrets of your patron's magic and learned a fundamental truth about your patron, even if their identity still remains a mystery. You gain an additional 10th-level spell slot.",
    "economy": "none",
    "trigger": ""
}