{
    "url": "https://2e.aonprd.com/Feats.aspx?ID=1332",
    "name": "Accursed Claws",
    "source": "Advanced Player's Guide",
    "rarity": "Common",
    "traits": [
        "Changeling"
    ],
    "level": 9,
    "prereq": "Claw Unarmed Attack",
    "summary": "Your claws carry your mother's hag magic.",
    "description": "Your claws carry your mother's hag magic. When you critically hit with a claw Strike, the target takes an additional 1d4 persistent mental damage.Traits\n\nChangeling: A creature with this trait has the changeling versatile heritage. Changelings are the children of hags and members of other humanoid ancestries. An ability with this trait can be used or selected only by changelings.",
    "economy": "none",
    "trigger": ""
}