{
    "url": "https://2e.aonprd.com/Spells.aspx?ID=60",
    "name": "Darkvision",
    "source": "Core Rulebook",
    "traditions": [
        "Arcane",
        "Divine",
        "Occult",
        "Primal"
    ],
    "rarity": "Common",
    "traits": [
        "Divination"
    ],
    "cantrip": false,
    "focus": false,
    "level": 2,
    "summary": "See in the dark.",
    "heightenable": true,
    "description": "You grant yourself supernatural sight in areas of darkness. You gain darkvision.\n\n------\n\nHeightened (3rd) The spell's range is touch and it targets 1 willing creature.\nHeightened (5th) The spell's range is touch and it targets 1 willing creature. The duration is until the next time you make your daily preparations.",
    "economy": "2-action",
    "components": [
        "Somatic",
        "Verbal"
    ],
    "trigger": "",
    "range": "",
    "target": "",
    "duration": "1 hour",
    "saving": ""
}